{
  "_fv": 47,
  "_type": "tool",
  "definition": {
    "toolType": "Sword",
    "renderType": 0,
    "texture": "drac_sword",
    "customModelName": "Normal",
    "name": "Draconite Sword",
    "specialInfo": [],
    "creativeTab": {
      "value": "CUSTOM:DracCreatTab"
    },
    "harvestLevel": 5,
    "efficiency": 10.0,
    "attackSpeed": 2.0,
    "enchantability": 20,
    "damageVsEntity": 8.0,
    "usageCount": 2500,
    "blocksAffected": [],
    "hasGlow": false,
    "repairItems": [],
    "immuneToFire": true,
    "stayInGridWhenCrafting": false,
    "damageOnCrafting": false
  }
}